{
   "data": [
      {
         "content": "this is update test for first one",
         "createdAt": "2019-10-12T07:28:02.350+0000",
         "id": 1,
         "title": "update checking docker",
         "updatedAt": "2019-10-12T07:28:02.350+0000"
      },
      {
         "content": "this is second note",
         "createdAt": "2019-10-27T04:41:04.501+0000",
         "id": 2,
         "title": "testV2",
         "updatedAt": "2019-10-27T04:41:04.501+0000"
      },
      {
         "content": "this is second note",
         "createdAt": "2019-10-27T04:42:14.647+0000",
         "id": 3,
         "title": "testV3",
         "updatedAt": "2019-10-27T04:42:14.647+0000"
      },
      {
         "content": "this is second note",
         "createdAt": "2019-10-27T04:43:41.545+0000",
         "id": 4,
         "title": "testV4",
         "updatedAt": "2019-10-27T04:43:41.545+0000"
      }
   ],
   "code": 0
}
